django_postges_lookups_any/__init__.py
django_postges_lookups_any/admin.py
django_postges_lookups_any/apps.py
django_postges_lookups_any/lookups.py
django_postges_lookups_any/models.py
django_postges_lookups_any/urls.py
django_postges_lookups_any/views.py
django_postges_lookups_any/test_utils/__init__.py
django_postges_lookups_any/test_utils/test_app/__init__.py
django_postges_lookups_any/test_utils/test_app/admin.py
django_postges_lookups_any/test_utils/test_app/apps.py
django_postges_lookups_any/test_utils/test_app/models.py
django_postges_lookups_any/test_utils/test_app/migrations/0001_initial.py
django_postges_lookups_any/test_utils/test_app/migrations/__init__.py
django_postges_lookups_any-0.1.2.dist-info/AUTHORS.rst
django_postges_lookups_any-0.1.2.dist-info/LICENSE
django_postges_lookups_any-0.1.2.dist-info/METADATA
django_postges_lookups_any-0.1.2.dist-info/WHEEL
django_postges_lookups_any-0.1.2.dist-info/top_level.txt
django_postges_lookups_any-0.1.2.dist-info/RECORD
