Metadata-Version: 2.1
Name: django-postges-lookups-any
Version: 0.1.2
Summary: Provides =ANY(ARRAY(xxx)) instead of IN (xxx)
Home-page: https://github.com/alexshin/django-postges-lookups-any
Author: Alex Shinkevich
Author-email: alex.shinkevich@gmail.com
License: MIT
Keywords: django-postges-lookups-any
Platform: UNKNOWN
Classifier: Framework :: Django :: 2.1
Classifier: Framework :: Django :: 2.2
Classifier: Framework :: Django :: 3.0
Classifier: Framework :: Django :: 3.1
Classifier: Intended Audience :: Developers
Classifier: License :: OSI Approved :: MIT License
Classifier: Natural Language :: English
Classifier: Programming Language :: Python :: 3.7
Classifier: Programming Language :: Python :: 3.8
Classifier: Programming Language :: Python :: 3.9
Requires-Dist: psycopg2
